anndata_tensorstore/__init__.py
anndata_tensorstore/_ext.py
anndata_tensorstore/_version.py
anndata_tensorstore-1.0.3.dist-info/METADATA
anndata_tensorstore-1.0.3.dist-info/WHEEL
anndata_tensorstore-1.0.3.dist-info/top_level.txt
anndata_tensorstore-1.0.3.dist-info/RECORD
